PyOCN/__init__.py
PyOCN/_flowgrid_convert.py
PyOCN/_libocn.cpython-311-darwin.so
PyOCN/_libocn_bindings.py
PyOCN/_statushandler.py
PyOCN/ocn.py
PyOCN/plotting.py
PyOCN/utils.py
PyOCN/c_src/build.sh
PyOCN/c_src/flowgrid.c
PyOCN/c_src/flowgrid.h
PyOCN/c_src/ocn.c
PyOCN/c_src/ocn.h
PyOCN/c_src/pyinit.c
PyOCN/c_src/rng.c
PyOCN/c_src/rng.h
PyOCN/c_src/status.c
PyOCN/c_src/status.h
pyocn-1.3.20251011.dist-info/licenses/LICENSE
pyocn-1.3.20251011.dist-info/METADATA
pyocn-1.3.20251011.dist-info/WHEEL
pyocn-1.3.20251011.dist-info/top_level.txt
pyocn-1.3.20251011.dist-info/RECORD
