Metadata-Version: 2.4
Name: PyOCN
Version: 1.3.20251011
Summary: Optimal Channel Networks (OCN) in Python with a C core
Author: Alexander S. Fox
License: GPL3
Project-URL: Repository, https://github.com/alextsfox/PyOCN
Project-URL: Documentation, https://pyocn.readthedocs.io
Project-URL: Changelog, https://github.com/alextsfox/PyOCN/blob/main/CHANGELOG.md
Requires-Python: >=3.10
License-File: LICENSE
Requires-Dist: numpy>=1.24
Requires-Dist: networkx>=3.1
Requires-Dist: tqdm>=4.44
Requires-Dist: matplotlib>=3.5
Provides-Extra: raster
Requires-Dist: rasterio>=1.3; extra == "raster"
Requires-Dist: xarray>=2024.2; extra == "raster"
Dynamic: license-file
